datafold_sdk/__init__.py
datafold_sdk/cli/__init__.py
datafold_sdk/cli/alerts.py
datafold_sdk/cli/ci.py
datafold_sdk/cli/cloud/__init__.py
datafold_sdk/cli/cloud/datafold_api.py
datafold_sdk/cli/config.py
datafold_sdk/cli/context.py
datafold_sdk/cli/dbt/__init__.py
datafold_sdk/cli/dbt_config_validators.py
datafold_sdk/cli/dbt_parser.py
datafold_sdk/cli/diff/__init__.py
datafold_sdk/cli/errors.py
datafold_sdk/cli/format.py
datafold_sdk/cli/monitors.py
datafold_sdk/cli/utils.py
datafold_sdk/sdk/__init__.py
datafold_sdk/sdk/ci/__init__.py
datafold_sdk/sdk/dbt/__init__.py
datafold_sdk/sdk/exceptions.py
datafold_sdk/sdk/utils.py
datafold_sdk/sdk_log.py
datafold_sdk/version.py
datafold_sdk/versions.py
datafold_mcp/__init__.py
datafold_mcp/auth/__init__.py
datafold_mcp/auth/token.py
datafold_mcp/client/__init__.py
datafold_mcp/client/api.py
datafold_mcp/config.py
datafold_mcp/server.py
datafold_mcp/tools/__init__.py
datafold_mcp/tools/data_sources.py
datafold_mcp/tools/datadiff.py
datafold_mcp/tools/query.py
datafold_sdk-0.1.0.dist-info/METADATA
datafold_sdk-0.1.0.dist-info/WHEEL
datafold_sdk-0.1.0.dist-info/entry_points.txt
datafold_sdk-0.1.0.dist-info/licenses/LICENSE
datafold_sdk-0.1.0.dist-info/RECORD
