Metadata-Version: 2.4
Name: datafold-sdk
Version: 0.1.0
Summary: The datafold SDK
License: MIT
License-File: LICENSE
Author: Datafold
Author-email: support@datafold.com
Requires-Python: >=3.11,<4.0
Classifier: License :: OSI Approved :: MIT License
Classifier: Operating System :: OS Independent
Classifier: Programming Language :: Python :: 3
Classifier: Programming Language :: Python :: 3.11
Classifier: Programming Language :: Python :: 3.12
Classifier: Programming Language :: Python :: 3.13
Classifier: Programming Language :: Python :: 3.14
Provides-Extra: mcp
Requires-Dist: attrs (>=23.1.0)
Requires-Dist: click (>=7.0)
Requires-Dist: dbt-core (>=1.0.0)
Requires-Dist: fastmcp (>=2.11.0) ; extra == "mcp"
Requires-Dist: httpx (>=0.25.0) ; extra == "mcp"
Requires-Dist: keyring
Requires-Dist: pydantic (>=2.0.0)
Requires-Dist: requests (>=2.20.0)
Requires-Dist: rich
Requires-Dist: tabulate (>=0.9.0)
Requires-Dist: toml (>=0.10.2)
Requires-Dist: typing-extensions (>=4.0.1)
Requires-Dist: urllib3
Project-URL: Homepage, https://pypi.org/project/datafold-sdk
